domini/__init__.py
domini/html/__init__.py
domini/html/events.py
domini/html/tags.py
domini/js/__init__.py
domini-0.11.0.dist-info/LICENSE
domini-0.11.0.dist-info/METADATA
domini-0.11.0.dist-info/WHEEL
domini-0.11.0.dist-info/RECORD
