Metadata-Version: 2.1
Name: domini
Version: 0.11.0
Summary: Create HTML documents using Pythonic syntax that mimics the real deal.
Home-page: https://gitlab.com/deepadmax/domini
License: GPL-3.0-or-later
Author: Maximillian Strand
Author-email: maxi@millian.se
Requires-Python: >=3.10,<4.0
Classifier: License :: OSI Approved :: GNU General Public License v3 or later (GPLv3+)
Classifier: Programming Language :: Python :: 3
Classifier: Programming Language :: Python :: 3.10
Classifier: Programming Language :: Python :: 3.11
Project-URL: Repository, https://gitlab.com/deepadmax/domini
